setup.py
distributions/Binomialdistribution.py
distributions/Gaussiandistribution.py
distributions/Generaldistribution.py
distributions/__init__.py
nikiema_distributions.egg-info/PKG-INFO
nikiema_distributions.egg-info/SOURCES.txt
nikiema_distributions.egg-info/dependency_links.txt
nikiema_distributions.egg-info/not-zip-safe
nikiema_distributions.egg-info/top_level.txt