Metadata-Version: 1.0
Name: nikiema-distributions
Version: 0.2
Summary: Gaussian and Binomial distributions
Home-page: UNKNOWN
Author: NIKIEMA Joshua
Author-email: joshuanikiema24@gmail.com
License: UNKNOWN
Platform: UNKNOWN
